tdtypes/__init__.py
tdtypes/column.py
tdtypes/finder.py
tdtypes/index.py
tdtypes/sqlcsr.py
tdtypes/table.py
tdtypes/tdconn_default.py
tdtypes/tdconn_tdodbc.py
tdtypes/tdfinder_default.py
tdtypes/tvm.py
tdtypes/util.py
tdtypes/tpt/__init__.py
tdtypes/tpt/cop.py
tdtypes/tpt/job.py
tdtypes/tpt/pop.py
tdtypes/tpt/sop.py
tdtypes/tpt/step.py
tdtypes/tpt/util.py
tdtypes-0.5.1.data/data/tdtypes/LICENSE
tdtypes-0.5.1.data/data/tdtypes/README.md
tdtypes-0.5.1.data/data/tdtypes/samples/pi_columns.py
tdtypes-0.5.1.data/data/tdtypes/samples/view_deps.py
tdtypes-0.5.1.dist-info/LICENSE
tdtypes-0.5.1.dist-info/METADATA
tdtypes-0.5.1.dist-info/WHEEL
tdtypes-0.5.1.dist-info/top_level.txt
tdtypes-0.5.1.dist-info/RECORD
