Metadata-Version: 2.1
Name: tdtypes
Version: 0.5.1
Summary: Database Types for Teradata
Home-page: https://bitbucket.org/padhia/tdtypes
Author: Paresh Adhia
License: MIT
Keywords: teradata
Platform: UNKNOWN
Classifier: Development Status :: 4 - Beta
Classifier: Intended Audience :: Developers
Classifier: License :: OSI Approved :: MIT License
Classifier: Topic :: Database
Classifier: Topic :: Software Development
Classifier: Programming Language :: Python :: 3 :: Only
Classifier: Programming Language :: Python :: 3.7
Classifier: Programming Language :: Python :: 3.8
Requires-Python: >=3.7
Requires-Dist: cached-property
Requires-Dist: teradatasql
